flexflow/__init__.py
flexflow/core/__init__.py
flexflow/core/flexflow_cbinding.py
flexflow/core/flexflow_logger.py
flexflow/core/flexflow_top.py
flexflow/core/flexflow_type.py
flexflow/core/legion_cffi.py
flexflow/keras/__init__.py
flexflow/keras/callbacks.py
flexflow/keras/initializers.py
flexflow/keras/losses.py
flexflow/keras/metrics.py
flexflow/keras/optimizers.py
flexflow/keras/backend/__init__.py
flexflow/keras/backend/flexflow_backend.py
flexflow/keras/datasets/__init__.py
flexflow/keras/datasets/cifar.py
flexflow/keras/datasets/cifar10.py
flexflow/keras/datasets/mnist.py
flexflow/keras/datasets/reuters.py
flexflow/keras/layers/__init__.py
flexflow/keras/layers/base_layer.py
flexflow/keras/layers/convolutional.py
flexflow/keras/layers/core.py
flexflow/keras/layers/input_layer.py
flexflow/keras/layers/merge.py
flexflow/keras/layers/normalization.py
flexflow/keras/layers/pool.py
flexflow/keras/models/__init__.py
flexflow/keras/models/base_model.py
flexflow/keras/models/model.py
flexflow/keras/models/sequential.py
flexflow/keras/models/tensor.py
flexflow/keras/preprocessing/__init__.py
flexflow/keras/preprocessing/sequence.py
flexflow/keras/preprocessing/text.py
flexflow/keras/utils/__init__.py
flexflow/keras/utils/data_utils.py
flexflow/keras/utils/generic_utils.py
flexflow/keras/utils/np_utils.py
flexflow/onnx/__init__.py
flexflow/onnx/model.py
flexflow/torch/__init__.py
flexflow/torch/fx.py
flexflow/torch/model.py
flexflow/torch/nn/__init__.py
flexflow/torch/nn/modules/__init__.py
flexflow/torch/nn/modules/module.py
flexflow-1.0.dist-info/METADATA
flexflow-1.0.dist-info/WHEEL
flexflow-1.0.dist-info/top_level.txt
flexflow-1.0.dist-info/RECORD
