Metadata-Version: 2.1
Name: flexflow
Version: 1.0
Summary: FlexFlow Python package
Home-page: https://github.com/flexflow/FlexFlow
License: Apache
Platform: UNKNOWN
Classifier: Programming Language :: Python :: 3.6
Classifier: License :: OSI Approved :: Apache Software License
Classifier: Operating System :: POSIX :: Linux
Classifier: Topic :: Software Development :: Libraries
Requires-Python: >=3.6
Requires-Dist: numpy (>=1.16)
Requires-Dist: cffi (>=1.11)
Requires-Dist: qualname
Requires-Dist: keras-preprocessing
Requires-Dist: Pillow
